pyversus-0.1.3.dist-info/licenses/LICENSE
versus/__init__.py
versus/examples.py
versus/comparison/__init__.py
versus/comparison/_exceptions.py
versus/comparison/_frames.py
versus/comparison/_inputs.py
versus/comparison/_relations.py
versus/comparison/_slices.py
versus/comparison/_sql.py
versus/comparison/_summary.py
versus/comparison/_types.py
versus/comparison/_validation.py
versus/comparison/_value_diffs.py
versus/comparison/_weave.py
versus/comparison/api.py
versus/comparison/comparison.py
pyversus-0.1.3.dist-info/METADATA
pyversus-0.1.3.dist-info/WHEEL
pyversus-0.1.3.dist-info/top_level.txt
pyversus-0.1.3.dist-info/RECORD
