Metadata-Version: 2.4
Name: pyversus
Version: 0.1.3
Summary: Compare two relations quickly using DuckDB
Author: versus authors
License-Expression: MIT
Project-URL: Homepage, https://eutwt.github.io/pyversus/
Project-URL: Documentation, https://eutwt.github.io/pyversus/
Project-URL: Repository, https://github.com/eutwt/pyversus
Requires-Python: >=3.7
License-File: LICENSE
Requires-Dist: duckdb>=1.0.0
Requires-Dist: typing-extensions>=4.0.0; python_version < "3.8"
Provides-Extra: docs
Requires-Dist: sphinx>=7.2; python_version >= "3.9" and extra == "docs"
Requires-Dist: pydata-sphinx-theme>=0.15.4; python_version >= "3.9" and extra == "docs"
Requires-Dist: numpydoc>=1.6; python_version >= "3.9" and extra == "docs"
Requires-Dist: sphinx-copybutton>=0.5.2; python_version >= "3.9" and extra == "docs"
Dynamic: license-file
